qbdquery/__init__.py
qbdquery/client.py
qbdquery/exceptions.py
qbdquery/query_builder.py
qbdquery-0.1.5.dist-info/licenses/LICENSE
qbdquery-0.1.5.dist-info/METADATA
qbdquery-0.1.5.dist-info/WHEEL
qbdquery-0.1.5.dist-info/top_level.txt
qbdquery-0.1.5.dist-info/RECORD
