Metadata-Version: 2.4
Name: qbdquery
Version: 0.1.5
Summary: A Python package for querying QuickBooks Desktop data
Author: Austin Rakowski
License: MIT
Project-URL: Homepage, https://github.com/austinrakowski/qbdquery
Project-URL: Issues, https://github.com/austinrakowski/qbdquery/issues
Keywords: quickbooks,qbd,quickbooks desktop,accounting,qbxml
Classifier: Development Status :: 3 - Alpha
Classifier: Intended Audience :: Developers
Classifier: License :: OSI Approved :: MIT License
Classifier: Programming Language :: Python :: 3
Classifier: Programming Language :: Python :: 3.7
Classifier: Programming Language :: Python :: 3.8
Classifier: Programming Language :: Python :: 3.9
Classifier: Programming Language :: Python :: 3.10
Classifier: Programming Language :: Python :: 3.11
Classifier: Programming Language :: Python :: 3.12
Classifier: Operating System :: Microsoft :: Windows
Classifier: Topic :: Office/Business :: Financial :: Accounting
Requires-Python: >=3.7
License-File: LICENSE
Requires-Dist: pywin32>=306
Dynamic: license-file
Dynamic: requires-python
